pyil2/__init__.py
pyil2/client.py
pyil2/enum.py
pyil2/api/__init__.py
pyil2/api/base.py
pyil2/api/chain.py
pyil2/api/documents.py
pyil2/api/json.py
pyil2/api/node.py
pyil2/api/opaque.py
pyil2/api/record.py
pyil2/models/__init__.py
pyil2/models/apps.py
pyil2/models/base.py
pyil2/models/chain.py
pyil2/models/documents.py
pyil2/models/errors.py
pyil2/models/json.py
pyil2/models/keys.py
pyil2/models/node.py
pyil2/models/record.py
pyil2/utils/__init__.py
pyil2/utils/certificates.py
pyil2/utils/range.py
pyil2-0.1.2.dist-info/LICENSE
pyil2-0.1.2.dist-info/METADATA
pyil2-0.1.2.dist-info/WHEEL
pyil2-0.1.2.dist-info/top_level.txt
pyil2-0.1.2.dist-info/RECORD
