Metadata-Version: 2.1
Name: pyil2
Version: 0.1.2
Summary: Python client to the InterlockLedger Node REST API
Home-page: https://github.com/interlockledger/py-interlockledger-rest-client
Author: InterlockLedger Network
Author-email: dchino@il2.io
Project-URL: Bug Tracker, https://github.com/interlockledger/py-interlockledger-rest-client/issues
Project-URL: Documentation, https://interlockledger.github.io/py-interlockledger-rest-client
Classifier: Programming Language :: Python :: 3
Classifier: License :: OSI Approved :: MIT License
Classifier: Operating System :: OS Independent
Requires-Python: >=3.11
License-File: LICENSE
Requires-Dist: pydantic >=2.6.1
Requires-Dist: requests ==2.32.2
Requires-Dist: pyOpenSSL >=24.1.0
Requires-Dist: pyilint >=0.2.2
Requires-Dist: pyiltags >=0.1.1
